{"noiseKey":{"private":{"type":"Buffer","data":"gJtB44hKQYy8BArQzuxjUECJbm8et+QSVlIoczb++EE="},"public":{"type":"Buffer","data":"Xszy8FKIPlFCTDy8GzU9xOYAe2YyofErDXxjL0NNrjw="}},"pairingEphemeralKeyPair":{"private":{"type":"Buffer","data":"cHtXRmANE2PiKrGCf+5qCq7ez6ANDcf5zQMHAEhG/F8="},"public":{"type":"Buffer","data":"1frJhR6qxRukNGcF0opXjwC0bvg33vWJEgcn+r0wcSc="}},"signedIdentityKey":{"private":{"type":"Buffer","data":"kB7fCgd25uKLZHaDY6+ZtfyHoC6IIT9S+F5WV4fZEFY="},"public":{"type":"Buffer","data":"gYYpFcSnCrdO5/mMC/Qvqx6dH0pZhnbGwnQHHgvlyys="}},"signedPreKey":{"keyPair":{"private":{"type":"Buffer","data":"gIEpI77i3O6uE8YB7OKodk5IbDI0RjOcnaQaigvFf2o="},"public":{"type":"Buffer","data":"BIlFhKZnnZmj/F6/Jec9bVWDtzyA1sNqn/sr3qoEKQA="}},"signature":{"type":"Buffer","data":"2ZMgl9qqH/7y+BzYsUcYX1swuhGYM8pdXaszhDHvK2O1iB/zRGCoAIMdsh8pq5lCWlvHax4MZQ+uK2oelTklig=="},"keyId":1},"registrationId":21,"advSecretKey":"TaAujM+LFacyMWXENbxwIaUk/mgiA/PRkfZHt3z02YQ=","processedHistoryMessages":[{"key":{"remoteJid":"243979414591@s.whatsapp.net","fromMe":true,"id":"3AEC02F05AF6F1F2574E"},"messageTimestamp":1737650178},{"key":{"remoteJid":"243979414591@s.whatsapp.net","fromMe":true,"id":"3A3D9F42C8B2BD3B09F8"},"messageTimestamp":1737650189},{"key":{"remoteJid":"243979414591@s.whatsapp.net","fromMe":true,"id":"3AA09AF6B8D80F3E4864"},"messageTimestamp":1737650210},{"key":{"remoteJid":"243979414591@s.whatsapp.net","fromMe":true,"id":"3A5E702A1765C78D9A2B"},"messageTimestamp":1737650230},{"key":{"remoteJid":"243979414591@s.whatsapp.net","fromMe":true,"id":"3A5072E1DDEA4BA53457"},"messageTimestamp":1737650240},{"key":{"remoteJid":"243979414591@s.whatsapp.net","fromMe":true,"id":"3A21CF0258EC874581C6"},"messageTimestamp":1737650249},{"key":{"remoteJid":"243979414591@s.whatsapp.net","fromMe":true,"id":"3ABA0E89AB141C239D59"},"messageTimestamp":1737650293},{"key":{"remoteJid":"243979414591@s.whatsapp.net","fromMe":true,"id":"3AF5647832C7AAF55D39"},"messageTimestamp":1737650293},{"key":{"remoteJid":"243979414591@s.whatsapp.net","fromMe":true,"id":"3AE94B70F178ABF3CEFC"},"messageTimestamp":1737650302},{"key":{"remoteJid":"243979414591@s.whatsapp.net","fromMe":true,"id":"3A1CEEC52A38F258831C"},"messageTimestamp":1737650399},{"key":{"remoteJid":"243979414591@s.whatsapp.net","fromMe":true,"id":"3ADEF30C0797D6D0689A"},"messageTimestamp":1737650420},{"key":{"remoteJid":"243979414591@s.whatsapp.net","fromMe":true,"id":"3AE5B9575296147AEF46"},"messageTimestamp":1737650420},{"key":{"remoteJid":"243979414591@s.whatsapp.net","fromMe":true,"id":"3AF4B5CD028AD4AE7F37"},"messageTimestamp":1737650424},{"key":{"remoteJid":"243979414591@s.whatsapp.net","fromMe":true,"id":"3A8EE54C6D2C18945643"},"messageTimestamp":1737650425}],"nextPreKeyId":122,"firstUnuploadedPreKeyId":122,"accountSyncCounter":1,"accountSettings":{"unarchiveChats":false},"registered":false,"account":{"details":"COjJ2aoCEPbfybwGGAEgACgA","accountSignatureKey":"JHYA1njgr2Y02NlCGXPyaRHehwpHHMAnZ1ETyZlOhA0=","accountSignature":"EejSK0qRhgP4wBpEJoD3ricWEkUGWyE19ejIp9kj1OPA6/B8QyG3wSi61NRup/6v3zEGqlxjKmNn+kQVnDApjQ==","deviceSignature":"bzoj0+eLVXn5y9D8FaVUJFI38fm6Aohphc8h/8Rsu0haQhDFY/r3c1ZYEWxp4n80qME81B7Mma8nq4r/GPfahw=="},"me":{"id":"243979414591:2@s.whatsapp.net","name":"ElectronicsMatters","lid":"158879748984845:2@lid"},"signalIdentities":[{"identifier":{"name":"243979414591:2@s.whatsapp.net","deviceId":0},"identifierKey":{"type":"Buffer","data":"BSR2ANZ44K9mNNjZQhlz8mkR3ocKRxzAJ2dRE8mZToQN"}}],"platform":"smbi","routingInfo":{"type":"Buffer","data":"CAkIAg=="},"lastAccountSyncTimestamp":1737932758,"lastPropHash":"nm3Bb","myAppStateKeyId":"AAAAAOsj"}